simplemfa/__init__.py
simplemfa/admin.py
simplemfa/apps.py
simplemfa/forms.py
simplemfa/helpers.py
simplemfa/middleware.py
simplemfa/models.py
simplemfa/tests.py
simplemfa/urls.py
simplemfa/views.py
simplemfa/migrations/0001_initial.py
simplemfa/migrations/__init__.py
simplemfa/templates/simplemfa/auth.html
simplemfa/templates/simplemfa/auth_email.html
simplemfa/templates/simplemfa/auth_text.html
simplemfa/templates/simplemfa/auth_voice.html
simplemfa/templates/simplemfa/mfa_base.html
django_simplemfa-0.4.1.dist-info/LICENSE
django_simplemfa-0.4.1.dist-info/METADATA
django_simplemfa-0.4.1.dist-info/WHEEL
django_simplemfa-0.4.1.dist-info/top_level.txt
django_simplemfa-0.4.1.dist-info/RECORD
