Metadata-Version: 2.1
Name: django-simplemfa
Version: 0.4.1
Summary: An implementation of essential multi-factor authentication (MFA) for django projects
Home-page: https://github.com/mwhawkins/django-simplemfa
Author: Michael Hawkins
Author-email: mhawkins@netizen.net
License: UNKNOWN
Platform: UNKNOWN
Classifier: Programming Language :: Python :: 3
Classifier: License :: OSI Approved :: MIT License
Classifier: Operating System :: OS Independent
Requires-Python: >=3.6
